labrynth/__init__.py
labrynth/__main__.py
labrynth/app.py
labrynth/data/__init__.py
labrynth/data/calendar_data.py
labrynth-0.0.1.dist-info/LICENSE
labrynth-0.0.1.dist-info/METADATA
labrynth-0.0.1.dist-info/WHEEL
labrynth-0.0.1.dist-info/top_level.txt
labrynth-0.0.1.dist-info/RECORD
