Metadata-Version: 2.1
Name: labrynth
Version: 0.0.1
Summary: A program that sets goals and helps you execute them.
Home-page: https://github.com/Alexangelj/Labrynth
Author: Alex Angel
Author-email: alexangel.j@gmail.com
License: UNKNOWN
Platform: UNKNOWN
Classifier: Programming Language :: Python :: 3.7
Classifier: License :: OSI Approved :: GNU General Public License v3 (GPLv3)
Requires-Dist: ipython (>=6)
Requires-Dist: nbformat (>=4)
Requires-Dist: nbconvert (>=5)
Requires-Dist: requests (>=2)
